{
    "ultima_actualizacion": "2026-05-21 22:23:31",
    "activos": {
        "argentina": {
            "YPF": {
                "precio": 47.94,
                "variacion_pct": 1.85
            },
            "GGAL": {
                "precio": 44.01,
                "variacion_pct": 4.74
            },
            "PAM": {
                "precio": 81.71,
                "variacion_pct": 2.86
            },
            "BMA": {
                "precio": 78.33,
                "variacion_pct": 8.63
            }
        },
        "global": {
            "SPY": {
                "precio": 742.72,
                "variacion_pct": 0.2
            },
            "QQQ": {
                "precio": 714.51,
                "variacion_pct": 0.19
            },
            "AAPL": {
                "precio": 304.99,
                "variacion_pct": 0.91
            },
            "MSFT": {
                "precio": 419.09,
                "variacion_pct": -0.47
            }
        }
    }
}